{
    "wallpaper": "https://imgapi.cn/api.php", 
    "sites": [
        {
            "key": "豆瓣", 
            "name": "豆瓣资源", 
            "type": 3, 
            "jar": "./jar/xingchen.jar",
            "api": "csp_Douban", 
            "searchable": 0
        },
        {
            "key": "晴天", 
            "name": "晴天4K", 
            "type": 3,  
            "jar": "./jar/xingchen.jar",
            "quickSearch": 1, 
            "api": "csp_AppGet", 
            "ext": {
                "url": "https://qjappcms.sun4k.top", 
                "dataKey": "sBxqXVF5pAHbGzrH", 
                "dataIv": "sBxqXVF5pAHbGzrH", 
                "deviceId": "", 
                "version": "119"
            }
        }, 
        {
            "key": "忍者", 
            "name": "忍者影视", 
            "type": 3,  
            "jar": "./jar/xingchen.jar",
            "quickSearch": 1, 
            "api": "csp_AppGet", 
            "ext": {
                "url": "https://mfxs123.sbs", 
                "dataKey": "1234567887654321", 
                "dataIv": "1234567887654321", 
                "deviceId": "", 
                "version": ""
            }
        }, 
        {
            "key": "布蕾", 
            "name": "布蕾影视", 
            "type": 3, 
            "api": "https://gitee.com/yuyu10588/tt/raw/t/t/drpy2.min.js", 
            "searchable": 1, 
            "quickSearch": 1, 
            "filterable": 1, 
            "order_num": 0, 
            "changeable": 0, 
            "ext": "http://150.158.112.123/公众号玉玉应用笔记/js/bulei.js"
        },
        {
            "key": "橘子", 
            "name": "橘子影视", 
            "type": 3,  
            "jar": "./jar/xingchen.jar",
            "quickSearch": 1, 
            "api": "csp_AppGet", 
            "ext": {
                "url": "https://api1.bffree.cn", 
                "dataKey": "2015692015692015", 
                "dataIv": "2015692015692015", 
                "deviceId": "", 
                "version": "300"
            }
        }, 
        {
            "key": "彼岸", 
            "name": "彼岸影视", 
            "type": 3,  
            "jar": "./jar/xingchen.jar",
            "quickSearch": 1, 
            "api": "csp_AppGet", 
            "ext": {
                "url": "http://172.247.44.217:30012", 
                "dataKey": "JLa1oRdL6+eK7@M)", 
                "dataIv": "JLa1oRdL6+eK7@M)", 
                "deviceId": "", 
                "version": ""
            }
        },
        {
            "key": "狐狸君", 
            "name": "狐狸4K", 
            "type": 3,  
            "jar": "./jar/xingchen.jar",
            "api": "csp_XBPQ", 
            "changeable": 1, 
            "searchable": 1, 
            "quickSearch": 1, 
            "filterable": 1, 
            "ext": "http://150.158.112.123/公众号玉玉应用笔记/js/6v.json"
        }, 
        {
            "key": "剧评", 
            "name": "剧评影视", 
            "type": 3,    
            "jar": "./jar/qji.jar",
            "api": "csp_Jpys", 
            "playerType": 1, 
            "ext": "7lj763gg402i7942463j9j9jh84l8798l8gli652828g332i"
        }, 
        {
            "key": "HD", 
            "name": "秒播影视", 
            "type": 3,    
            "jar": "./jar/mbo.jar",
            "api": "csp_Hudie",
            "playerType": 2, 
            "ext": "eaHR0cHM6Ly9kLmRjbW92aWUudG9w"
        },
        {
            "key": "小红", 
            "name": "小红影视", 
            "type": 3,  
            "jar": "./jar/xingchen.jar",
            "api": "csp_AppGet", 
            "ext": {
                "url": "https://www.xiaohys.com", 
                "dataKey": "ENonBHeVBoYZhVUV", 
                "dataIv": "ENonBHeVBoYZhVUV", 
                "deviceId": "298e5fe29c74b35aabb9836ee2f6f449f", 
                "version": "166"
            }
        }, 
        {
            "key": "csp_CZSPP", 
            "name": "厂长影视", 
            "type": 3, 
            "api": "csp_Czsapp", 
            "jar": "http://cdn.qiaoji8.com/fix250410.jar;md5;bb362e424047eec85220dc5aa1066896", 
            "searchable": 1, 
            "playerType": 1, 
            "quickSearch": 1, 
            "filterable": 0, 
            "ext": "7lj763gg402i7942463j9j9jh346968hg5ll845ki38473"
        },
        {
            "key": "快看影视", 
            "name": "快看影视", 
            "type": 3,  
            "jar": "./jar/xingchen.jar",
            "api": "csp_Kuaikan", 
            "searchable": 1, 
            "quickSearch": 1, 
            "filterable": 1, 
            "jar": "https://gitee.com/hushujiang/diyp/raw/master/jar.php"
        }, 
        {
            "key": "尘落影视", 
            "name": "尘落影视", 
            "type": 3,  
            "jar": "./jar/xingchen.jar",
            "api": "csp_Wetv", 
            "searchable": 1, 
            "quickSearch": 1, 
            "ext": "https://v.wetv.wang", 
            "jar": "https://gitee.com/hushujiang/diyp/raw/master/jar.php"
        }, 
        {
            "key": "浪酷影视", 
            "name": "浪酷影视", 
            "type": 3,  
            "jar": "./jar/xingchen.jar",
            "api": "csp_AppRJ", 
            "searchable": 1, 
            "quickSearch": 1, 
            "filterable": 0, 
            "ext": {
                "url": "http://v.lkuys.cn"
            }
        },
        {
            "key": "天天", 
            "name": "天天影视", 
            "type": 3,  
            "jar": "./jar/xingchen.jar",
            "api": "csp_AppRJ", 
            "searchable": 1, 
            "quickSearch": 1, 
            "filterable": 0, 
            "ext": {
                "url": "http://tt.ysdqjs.cn"
            }
        },
        {
            "key": "白白影视", 
            "name": "白白影视", 
            "type": 3,  
            "jar": "./jar/xingchen.jar",
            "api": "csp_SuBaiBai", 
            "ext": "https://www.subaibai.com"
        }, 
        {
            "key": "骚火影视", 
            "name": "骚火影视", 
            "type": 3,  
            "jar": "./jar/xingchen.jar",
            "api": "csp_XYQHiker", 
            "searchable": 1, 
            "quickSearch": 1, 
            "filterable": 1, 
            "ext": "http://150.158.112.123/公众号玉玉应用笔记/js/saohuo.json"
        },
        {
            "key": "星河", 
            "name": "星河影视", 
            "type": 3,  
            "jar": "./jar/xingchen.jar",
            "quickSearch": 1, 
            "api": "csp_AppGet", 
            "ext": {
                "url": "http://121.62.22.204:9876", 
                "dataKey": "f5e2tx53ykp6s2c9", 
                "dataIv": "f5e2tx53ykp6s2c9", 
                "deviceId": "", 
                "version": "361"
            }
        },
        {
            "key": "苹果影视", 
            "name": "苹果影视", 
            "type": 3,  
            "jar": "./jar/xingchen.jar",
            "api": "csp_LiteApple", 
            "searchable": 1, 
            "quickSearch": 1, 
            "filterable": 1
        },
        {
            "key": "荐片", 
            "name": "荐片磁力", 
            "api": "csp_Jianpian", 
            "type": 3,  
            "jar": "./jar/xingchen.jar",
            "playerType": 1, 
            "ext": "http://api2.rinhome.com"
        }, 
        {
            "key": "drpyS_5点电影[S]", 
            "name": "五点电影", 
            "type": 4, 
            "api": "http://117.72.120.174:5757/api/5点电影[S]?pwd=zy", 
            "searchable": 1, 
            "filterable": 1, 
            "quickSearch": 1, 
            "ext": ""
        }, 
        {
            "key": "海纳TV", 
            "name": "海纳影视", 
            "type": 3,  
            "jar": "./jar/xingchen.jar",
            "api": "csp_XBPQ", 
            "ext": {
                "主页url": "https://hainatv.net/", 
                "分类url": "https://hainatv.net/index.php/vod/show/area/{area}/by/{by}/id/{cateId}/lang/{lang}/letter/{letter}/page/{catePg}/year/{year}.html", 
                "分类": "电影$1#剧集$2#综艺$3#动漫$4#短剧$59#解说$64"
            }
        }, 
        {
            "key": "一个G", 
            "name": "毅哥蓝光", 
            "type": 3,  
            "jar": "./jar/xingchen.jar",
            "api": "csp_XBPQ", 
            "searchable": 1, 
            "quickSearch": 1, 
            "filterable": 1, 
            "ext": {
                "影片地区": "艾丝沐制作", 
                "影片年代": "<div class=\"module-info-tag\">&&</div>", 
                "影片状态": "备注：&&</div>", 
                "影片类型": "module-info-tag\">&&立即播放", 
                "简介": "关注公众号：艾丝沐。+style=\"line-height: 20px;\"&&</div>", 
                "线路数组": "data-dropdown-value=&&</div>", 
                "线路标题": "<span>&&</span>", 
                "分类url": "https://www.ddmf.net/vodshow/1-----------/area/{area}/by/{by}/class/{class}/id/{cateId}/page/{catePg}/year/{year}.html", 
                "分类": "电影$1#电视剧$2#动漫$4#综艺$3"
            }
        },
        {
            "key": "FourKTV", 
            "name": "复刻影视", 
            "type": 3,  
            "api": "csp_FourKTV", 
            "jar": "./jar/oo.jar", 
            "playerType": 2, 
            "searchable": 1, 
            "quickSearch": 1, 
            "changeable": 1
        }, 
        {
            "key": "低端影视", 
            "name": "低端影视", 
            "type": 3,  
            "api": "csp_Ddys", 
            "jar": "./jar/o.jar", 
            "searchable": 1, 
            "quickSearch": 1, 
            "filterable": 1
        }, 
        {
            "key": "蝴蝶", 
            "name": "蝴蝶影视", 
            "type": 3,  
            "api": "csp_Hudie", 
            "jar": "./jar/o.jar", 
            "playerType": 2, 
            "ext": "eaHR0cHM6Ly9kLmRjbW92aWUudG9w"
        }, 
        {
            "key": "暴风资源", 
            "name": "暴风资源", 
            "type": 1, 
            "api": "https://bfzyapi.com/api.php/provide/vod/", 
            "playUrl": "https://vip.vipuuvip.com/?url=", 
            "searchable": 1, 
            "quickSearch": 1, 
            "filterable": 1
        }, 
        {
            "key": "卧龙资源", 
            "name": "卧龙资源", 
            "type": 1, 
            "api": "https://collect.wolongzyw.com/api.php/provide/vod/", 
            "searchable": 1, 
            "quickSearch": 1, 
            "filterable": 1
        }, 
        {
            "key": "量子资源", 
            "name": "量子资源", 
            "type": 1, 
            "api": "http://cj.lziapi.com/api.php/provide/vod/", 
            "searchable": 1, 
            "quickSearch": 1, 
            "filterable": 1
        }, 
        {
            "key": "360资源", 
            "name": "360资源", 
            "type": 1, 
            "api": "https://360zy.com/api.php/seaxml/vod", 
            "searchable": 1, 
            "quickSearch": 1, 
            "filterable": 1
        }, 
        {
            "key": "华为资源", 
            "name": "华为资源", 
            "type": 1, 
            "api": "https://hw8.live/api.php/provide/vod", 
            "searchable": 1, 
            "quickSearch": 1, 
            "filterable": 1
        }, 
        {
            "key": "无尽资源", 
            "name": "无尽资源", 
            "type": 1, 
            "api": "https://api.wujinapi.me/api.php/provide/vod", 
            "searchable": 1, 
            "quickSearch": 1, 
            "filterable": 1
        }, 
        {
            "key": "最大资源", 
            "name": "最大资源", 
            "type": 1, 
            "api": "https://api.zuidapi.com/api.php/provide/vod/", 
            "searchable": 1, 
            "quickSearch": 1, 
            "filterable": 1
        },
        {
            "key": "drpyS_星芽短剧[短]", 
            "name": "星芽短剧", 
            "type": 4, 
            "api": "https://zhxy.eu.org/api/星芽短剧[短]", 
            "searchable": 2, 
            "filterable": 1, 
            "quickSearch": 1, 
            "ext": ""
        },
        {
            "key": "星芽", 
            "name": "星芽短剧", 
            "type": 3,  
            "jar": "./jar/xingchen.jar",
            "api": "csp_AppXY", 
            "searchable": 1, 
            "quickSearch": 0, 
            "filterable": 0
        },
        {
            "key": "哔哩哔哩", 
            "name": "哔哩分类", 
            "type": 3,  
            "jar": "./jar/xingchen.jar",
            "api": "csp_Bili", 
            "jar": "https://cik03-cos.7moor-fs1.com/im/4d2c3f00-7d4c-11e5-af15-41bf63ae4ea0/c8fd2c83-7f26-4d9a-983c-042d25692adf/2024-06-18/2024-06-18_00:47:33/1718642853998/96346083/duo.jar;md5;5C5116C70E15343433C8480C3B448408", 
            "searchable": 1, 
            "quickSearch": 1, 
            "changeable": 2, 
            "filterable": 1, 
            "ext": "https://image-c.weimobwmc.com/ol-OlSf/58cbbf5395d4468cb4180b57c2834102.jpg"
        }, 
        {
            "key": "相声小品", 
            "name": "相声小品", 
            "type": 3,  
            "jar": "./jar/xingchen.jar",
            "api": "csp_Bili", 
            "jar": "https://cik03-cos.7moor-fs1.com/im/4d2c3f00-7d4c-11e5-af15-41bf63ae4ea0/c8fd2c83-7f26-4d9a-983c-042d25692adf/2024-06-18/2024-06-18_00:47:33/1718642853998/96346083/duo.jar;md5;5C5116C70E15343433C8480C3B448408", 
            "searchable": 0, 
            "quickSearch": 1, 
            "filterable": 1, 
            "ext": "https://image-c.weimobwmc.com/ol-OlSf/5e6fa3015aad4fa1956ed181cfaf172b.jpg"
        }, 
        {
            "key": "drpy_js_蜻蜓FM", 
            "name": "蜻蜓广播", 
            "type": 3, 
            "api": "https://gitee.com/yuyu10588/tt/raw/t/t/drpy2.min.js", 
            "ext": "http://150.158.112.123/公众号玉玉应用笔记/js/qingting.js"
        },
        {
            "key": "戏曲", 
            "name": "戏曲大全", 
            "type": 3,  
            "jar": "./jar/xingchen.jar",
            "api": "csp_Bili", 
            "jar": "https://cik03-cos.7moor-fs1.com/im/4d2c3f00-7d4c-11e5-af15-41bf63ae4ea0/c8fd2c83-7f26-4d9a-983c-042d25692adf/2024-06-18/2024-06-18_00:47:33/1718642853998/96346083/duo.jar;md5;5C5116C70E15343433C8480C3B448408", 
            "searchable": 0, 
            "quickSearch": 1, 
            "filterable": 1, 
            "ext": "https://image-c.weimobwmc.com/ol-OlSf/9a72ac3a9fa24d3f84cebcf008e4ed0d.jpg"
        }, 
        {
            "key": "梨园", 
            "name": "梨园戏曲", 
            "type": 3, 
            "api": "https://gitee.com/yuyu10588/tt/raw/t/t/drpy2.min.js", 
            "searchable": 1, 
            "quickSearch": 1, 
            "filterable": 1, 
            "ext": "https://image-c.weimobwmc.com/ol-OlSf/983ec95b8248461cad620063864b21cd.jpg"
        },
        {
            "key": "drpyS_KTV歌厅[听]", 
            "name": "MV音乐", 
            "type": 4, 
            "api": "https://zhxy.eu.org/api/KTV歌厅[听]", 
            "searchable": 2, 
            "filterable": 1, 
            "quickSearch": 0, 
            "ext": ""
        }, 
        {
            "key": "hipy_js_种子音乐[听]", 
            "name": "种子音乐", 
            "type": 3, 
            "api": "https://gitee.com/yuyu10588/tt/raw/t/t/drpy2.min.js", 
            "searchable": 1, 
            "quickSearch": 1, 
            "filterable": 1, 
            "order_num": 0, 
            "ext": "http://150.158.112.123/公众号玉玉应用笔记/js/zhongzi.js"
        }
    ], 
    "logo": "https://d.kstore.dev/download/6474/tvbox/img/v0.png", 
    "parses": [
        {
            "name": "轮询优选", 
            "type": 2, 
            "url": "Sequence"
        }, 
        {
            "name": "影视", 
            "type": 0, 
            "url": "https://jx.xmflv.com/?url=", 
            "ext": {
                "header": {
                    "user-agent": "Mozilla/5.0 (Windows NT 10.0; Win64; x64) AppleWebKit/537.36 (KHTML, like Gecko) Chrome/110.0.0.0 Safari/537.36 Edg/110.0.1587.57"
                }
            }
        }, 
        {
            "name": "影视2", 
            "type": 1, 
            "url": "https://150.138.78.37:4399/api?key=2b879e7ecc09a112c1d9f85c42967aca&url=", 
            "ext": {
                "flag": [
                    "qq", 
                    "腾讯", 
                    "qiyi", 
                    "爱奇艺", 
                    "奇艺", 
                    "youku", 
                    "优酷", 
                    "sohu", 
                    "搜狐", 
                    "letv", 
                    "乐视", 
                    "mgtv", 
                    "芒果", 
                    "tnmb", 
                    "seven", 
                    "bilibili", 
                    "1905"
                ], 
                "header": {
                    "User-Agent": "okhttp/4.9.1"
                }
            }
        }
    ], 
    "lives": [
   {
      "name": "543",
      "url": "http://99.iptv543.com/4gtv.m3u",
      "epg": "http://epg.112114.xyz/?ch={name}&date={date}",
      "logo": "https://epg.112114.xyz/logo/{name}.png"
    
    },
        {
            "name": "平台直播", 
            "type": 0, 
            "url": "http://150.158.112.123/live.txt", 
            "ua": "okhttp/3.15", 
            "playerType": 2
        }
    ]
}
